hooks/__init__.py
hooks/apps/__init__.py
hooks/apps/startup/__init__.py
hooks/apps/startup/apps.py
hooked_on_django-0.2.0.dist-info/LICENSE
hooked_on_django-0.2.0.dist-info/WHEEL
hooked_on_django-0.2.0.dist-info/METADATA
hooked_on_django-0.2.0.dist-info/RECORD
