Metadata-Version: 2.1
Name: hooked-on-django
Version: 0.2.0
Summary: Simple django application to trigger hooked methods.
Home-page: https://github.com/fedecalendino/hooked-on-django
License: MIT
Keywords: django,hooks,startup
Author: Fede Calendino
Author-email: fede@calendino.com
Requires-Python: >=3.8,<4.0
Classifier: Intended Audience :: Developers
Classifier: License :: OSI Approved :: MIT License
Classifier: Programming Language :: Python :: 3
Classifier: Programming Language :: Python :: 3.10
Classifier: Programming Language :: Python :: 3.8
Classifier: Programming Language :: Python :: 3.9
Requires-Dist: django (>=4.0.6,<5.0.0)
Project-URL: Documentation, https://github.com/fedecalendino/hooked-on-django/blob/main/README.md
